{
  "sb_watermelon_1769726788": {
    "id": "sb_watermelon_1769726788",
    "food_name": "watermelon",
    "food_name_kr": "수박",
    "approval_type": "storyboard",
    "status": "approved",
    "requester": "system",
    "reviewer": "test_user",
    "created_at": "2026-01-30T07:46:28.982580",
    "reviewed_at": null,
    "feedback": null,
    "message_ts": "local",
    "channel_id": "local",
    "tech_score": null,
    "creative_score": null
  },
  "final_banana_1769726788": {
    "id": "final_banana_1769726788",
    "food_name": "banana",
    "food_name_kr": "바나나",
    "approval_type": "final",
    "status": "rejected",
    "requester": "system",
    "reviewer": "test_reviewer",
    "created_at": "2026-01-30T07:46:28.982792",
    "reviewed_at": "2026-01-30T07:46:28.982915",
    "feedback": "품질 기준 미달",
    "message_ts": "local",
    "channel_id": "local",
    "tech_score": 75.0,
    "creative_score": 70.0
  }
}